{ "frames": {
   "Eye 0.aseprite": {
    "frame": { "x": 0, "y": 0, "w": 400, "h": 400 },
    "rotated": false,
    "trimmed": false,
    "spriteSourceSize": { "x": 0, "y": 0, "w": 400, "h": 400 },
    "sourceSize": { "w": 400, "h": 400 },
    "duration": 100
   },
   "Eye 1.aseprite": {
    "frame": { "x": 400, "y": 0, "w": 400, "h": 400 },
    "rotated": false,
    "trimmed": false,
    "spriteSourceSize": { "x": 0, "y": 0, "w": 400, "h": 400 },
    "sourceSize": { "w": 400, "h": 400 },
    "duration": 100
   },
   "Eye 2.aseprite": {
    "frame": { "x": 800, "y": 0, "w": 400, "h": 400 },
    "rotated": false,
    "trimmed": false,
    "spriteSourceSize": { "x": 0, "y": 0, "w": 400, "h": 400 },
    "sourceSize": { "w": 400, "h": 400 },
    "duration": 100
   },
   "Eye 3.aseprite": {
    "frame": { "x": 1200, "y": 0, "w": 400, "h": 400 },
    "rotated": false,
    "trimmed": false,
    "spriteSourceSize": { "x": 0, "y": 0, "w": 400, "h": 400 },
    "sourceSize": { "w": 400, "h": 400 },
    "duration": 100
   },
   "Eye 4.aseprite": {
    "frame": { "x": 1600, "y": 0, "w": 400, "h": 400 },
    "rotated": false,
    "trimmed": false,
    "spriteSourceSize": { "x": 0, "y": 0, "w": 400, "h": 400 },
    "sourceSize": { "w": 400, "h": 400 },
    "duration": 100
   },
   "Eye 5.aseprite": {
    "frame": { "x": 0, "y": 400, "w": 400, "h": 400 },
    "rotated": false,
    "trimmed": false,
    "spriteSourceSize": { "x": 0, "y": 0, "w": 400, "h": 400 },
    "sourceSize": { "w": 400, "h": 400 },
    "duration": 100
   },
   "Eye 6.aseprite": {
    "frame": { "x": 400, "y": 400, "w": 400, "h": 400 },
    "rotated": false,
    "trimmed": false,
    "spriteSourceSize": { "x": 0, "y": 0, "w": 400, "h": 400 },
    "sourceSize": { "w": 400, "h": 400 },
    "duration": 100
   },
   "Eye 7.aseprite": {
    "frame": { "x": 800, "y": 400, "w": 400, "h": 400 },
    "rotated": false,
    "trimmed": false,
    "spriteSourceSize": { "x": 0, "y": 0, "w": 400, "h": 400 },
    "sourceSize": { "w": 400, "h": 400 },
    "duration": 100
   }
 },
 "meta": {
  "app": "http://www.aseprite.org/",
  "version": "1.2.9-x64",
  "image": "C:\\Repos\\how-not-to-use-a-phone\\magnets\\Assets\\RedDirt\\Images\\Eye.png",
  "format": "RGBA8888",
  "size": { "w": 2048, "h": 1024 },
  "scale": "1",
  "frameTags": [
   { "name": "EyeClosed", "from": 0, "to": 1, "direction": "forward" },
   { "name": "EyeOpening", "from": 2, "to": 3, "direction": "forward" },
   { "name": "EyeOpen", "from": 4, "to": 5, "direction": "forward" },
   { "name": "EyeClosing", "from": 6, "to": 7, "direction": "forward" }
  ],
  "layers": [
   { "name": "Layer 1", "opacity": 255, "blendMode": "normal" }
  ],
  "slices": [
  ]
 }
}
